adata/__init__.py
adata/client.py
adata/consts.py
adata/iterators.py
alpha_data_py-1.0.14.dist-info/METADATA
alpha_data_py-1.0.14.dist-info/WHEEL
alpha_data_py-1.0.14.dist-info/top_level.txt
alpha_data_py-1.0.14.dist-info/RECORD
