Metadata-Version: 2.1
Name: alpha-data-py
Version: 1.0.14
Summary: client to communicate with alphaticks
Home-page: https://gitlab.com/alphaticks/alpha-data-py
Author: Alphaticks
License: copyright
Requires-Dist: alpha-public-registry-grpc (==1.0.3)
Requires-Dist: tickstore-python-client (==1.0.5)
